cryptota/__init__.py
cryptota/main.py
cryptota/pantulipy.py
cryptota-0.0.5.dist-info/LICENSE
cryptota-0.0.5.dist-info/METADATA
cryptota-0.0.5.dist-info/WHEEL
cryptota-0.0.5.dist-info/top_level.txt
cryptota-0.0.5.dist-info/RECORD
