Metadata-Version: 2.1
Name: cryptota
Version: 0.0.5
Summary: UNKNOWN
Home-page: https://github.com/voidful/CryptoTA
Author: Voidful
Author-email: voidful.stack@gmail.com
License: Apache
Keywords: Crypto
Platform: UNKNOWN
Classifier: Development Status :: 4 - Beta
Classifier: License :: OSI Approved :: Apache Software License
Classifier: Programming Language :: Python
License-File: LICENSE
Requires-Dist: tulipy
Requires-Dist: numpy (>=1.20.0)
Requires-Dist: pyyaml (==5.4.1)
Requires-Dist: pandas
Requires-Dist: pandas-ta
Requires-Dist: vectorbt
Requires-Dist: python-binance
Requires-Dist: alpaca-trade-api
Requires-Dist: ccxt (>=1.74.63)
Requires-Dist: yfinance
